nginx_generator/__init__.py
nginx_generator/app.py
nginx_generator/snippets/about
nginx_generator/snippets/php-fpm
nginx_generator/snippets/proxy_settings
nginx_generator-0.1.5.dist-info/METADATA
nginx_generator-0.1.5.dist-info/WHEEL
nginx_generator-0.1.5.dist-info/entry_points.txt
nginx_generator-0.1.5.dist-info/top_level.txt
nginx_generator-0.1.5.dist-info/RECORD
