Metadata-Version: 2.1
Name: nginx-generator
Version: 0.1.5
Summary: Generate nginx configs interactivly
Author: Oliwerix
Author-email: oliwerix@oliwerix.com
License: AGPLv3.0-or-later
Keywords: nginx,config,configuration,block
Platform: UNKNOWN
Requires-Python: >=3.7
Requires-Dist: click
Requires-Dist: validators
